ds_catalog/__init__.py
ds_catalog/api/__init__.py
ds_catalog/api/catalog_api.py
ds_catalog/api/catalog_items_api.py
ds_catalog/api/catalog_items_data_api.py
ds_catalog/api/catalog_items_importing_api.py
ds_catalog/api/catalog_items_sharing_api.py
ds_catalog/api/datasets_api.py
ds_catalog/api/default_api.py
ds_catalog/api/importing_api.py
ds_catalog/api/mmio_api.py
ds_catalog/api/sharing_api.py
ds_catalog/api_client.py
ds_catalog/api_response.py
ds_catalog/configuration.py
ds_catalog/exceptions.py
ds_catalog/models/__init__.py
ds_catalog/models/catalog.py
ds_catalog/models/catalog_filters.py
ds_catalog/models/catalog_import_form.py
ds_catalog/models/catalog_item.py
ds_catalog/models/catalog_item_form.py
ds_catalog/models/catalog_item_import_form.py
ds_catalog/models/catalog_item_share_form.py
ds_catalog/models/checksum.py
ds_catalog/models/connector.py
ds_catalog/models/created.py
ds_catalog/models/created_gte.py
ds_catalog/models/created_lte.py
ds_catalog/models/creator_id.py
ds_catalog/models/data_product.py
ds_catalog/models/data_product_form.py
ds_catalog/models/data_service.py
ds_catalog/models/dataproduct_size_gte.py
ds_catalog/models/dataproduct_size_lte.py
ds_catalog/models/dataset.py
ds_catalog/models/dataset_form.py
ds_catalog/models/dataset_import_form.py
ds_catalog/models/dataset_share_form.py
ds_catalog/models/distribution.py
ds_catalog/models/error_response.py
ds_catalog/models/health_check.py
ds_catalog/models/http_validation_error.py
ds_catalog/models/interface.py
ds_catalog/models/islocal.py
ds_catalog/models/isshared.py
ds_catalog/models/node.py
ds_catalog/models/ontology.py
ds_catalog/models/ontology1.py
ds_catalog/models/order_direction.py
ds_catalog/models/orderdirection.py
ds_catalog/models/page.py
ds_catalog/models/pagesize.py
ds_catalog/models/paginated_result_catalog_item.py
ds_catalog/models/paginated_result_dataset.py
ds_catalog/models/person.py
ds_catalog/models/size.py
ds_catalog/models/source.py
ds_catalog/models/source_interface.py
ds_catalog-0.2.2.dist-info/LICENSE
ds_catalog-0.2.2.dist-info/METADATA
ds_catalog-0.2.2.dist-info/WHEEL
ds_catalog-0.2.2.dist-info/RECORD
